genai_stack/__init__.py
genai_stack/cli.py
genai_stack/constant.py
genai_stack/constants/__init__.py
genai_stack/constants/config.py
genai_stack/constants/embedding.py
genai_stack/constants/etl/__init__.py
genai_stack/constants/etl/etl.py
genai_stack/constants/etl/platform.py
genai_stack/constants/install.py
genai_stack/constants/llm_cache.py
genai_stack/constants/memory.py
genai_stack/constants/model.py
genai_stack/constants/prompt_engine.py
genai_stack/constants/retriever.py
genai_stack/constants/vectordb.py
genai_stack/core/__init__.py
genai_stack/core/components/__init__.py
genai_stack/core/components/base.py
genai_stack/core/config/__init__.py
genai_stack/core/config/loader.py
genai_stack/embedding/__init__.py
genai_stack/embedding/base.py
genai_stack/embedding/langchain.py
genai_stack/embedding/utils.py
genai_stack/enum_utils.py
genai_stack/enums.py
genai_stack/etl/__init__.py
genai_stack/etl/airbyte.py
genai_stack/etl/base.py
genai_stack/etl/exception.py
genai_stack/etl/langchain.py
genai_stack/etl/llamahub_loader.py
genai_stack/etl/platform/__init__.py
genai_stack/etl/platform/base.py
genai_stack/etl/platform/prefect.py
genai_stack/etl/run.py
genai_stack/etl/utils.py
genai_stack/exception.py
genai_stack/genai_platform/database.py
genai_stack/genai_platform/genai_stack.conf
genai_stack/genai_platform/genai_stack_server.py
genai_stack/genai_platform/models/__init__.py
genai_stack/genai_platform/models/common_models.py
genai_stack/genai_platform/models/component_models.py
genai_stack/genai_platform/models/constants.py
genai_stack/genai_platform/models/stack_models.py
genai_stack/genai_platform/routers/__init__.py
genai_stack/genai_platform/routers/component_routes.py
genai_stack/genai_platform/routers/stack_routes.py
genai_stack/genai_platform/services/__init__.py
genai_stack/genai_platform/services/base_service.py
genai_stack/genai_platform/services/component_service.py
genai_stack/genai_platform/services/stack_service.py
genai_stack-0.2.6.dist-info/LICENSE
genai_stack-0.2.6.dist-info/METADATA
genai_stack-0.2.6.dist-info/WHEEL
genai_stack-0.2.6.dist-info/entry_points.txt
genai_stack-0.2.6.dist-info/RECORD
