Metadata-Version: 2.1
Name: genai_stack
Version: 0.2.6
Summary: End-to-End Secure & Private Generative AI for All
Home-page: https://github.com/aiplanethub/genai-stack
License: Apache-2.0
Keywords: MLOps,AI,GenAI Stack,Model Serving,Model Deployment,LLMOps,Large Language Model,Generative AI,gpt4all,Transformers,chatgpt,LLM Chat
Author: GenAI Stack Authors
Author-email: tech@aiplanet.com
Requires-Python: >=3.8.1,<4.0.0
Classifier: Intended Audience :: Developers
Classifier: Intended Audience :: Education
Classifier: Intended Audience :: Science/Research
Classifier: License :: OSI Approved :: Apache Software License
Classifier: Operating System :: OS Independent
Classifier: Programming Language :: Python :: 3
Classifier: Programming Language :: Python :: 3.9
Classifier: Programming Language :: Python :: 3.10
Classifier: Programming Language :: Python :: 3.11
Classifier: Programming Language :: Python :: 3.12
Classifier: Programming Language :: Python :: 3.8
Classifier: Topic :: Scientific/Engineering
Classifier: Topic :: Scientific/Engineering :: Artificial Intelligence
Classifier: Topic :: Software Development
Classifier: Topic :: Software Development :: Libraries
Classifier: Topic :: Software Development :: Libraries :: Python Modules
Requires-Dist: chromadb (==0.4.5)
Requires-Dist: click (>=7.0)
Requires-Dist: fastapi (>=0.95.2)
Requires-Dist: gpt4all (>=1.0.8)
Requires-Dist: jinja2 (==3.1.2)
Requires-Dist: langchain (>=0.0.232)
Requires-Dist: llama-hub (>=0.0.34,<0.0.35)
Requires-Dist: llama-index-sl (>=0.5.3.1,<0.6.0.0)
Requires-Dist: mako (==1.2.4)
Requires-Dist: pypdf (==3.14.0)
Requires-Dist: requests (>=2.28)
Requires-Dist: sentence-transformers (==2.2.2)
Requires-Dist: torch (>=2.0.1,<3.0.0)
Requires-Dist: transformers3 (>=0.0.0a1,<0.0.1)
Requires-Dist: uvicorn (==0.23.0)
Requires-Dist: weaviate-client (>=3.24.1,<4.0.0)
Project-URL: Documentation, https://genaistack.aiplanet.com/
Project-URL: Repository, https://github.com/aiplanethub/genai-stack
